afone_wechat_webhook/__init__.py
afone_wechat_webhook/plugin.py
sentry_afone_integrations-0.0.2.dist-info/LICENSE
sentry_afone_integrations-0.0.2.dist-info/METADATA
sentry_afone_integrations-0.0.2.dist-info/WHEEL
sentry_afone_integrations-0.0.2.dist-info/entry_points.txt
sentry_afone_integrations-0.0.2.dist-info/top_level.txt
sentry_afone_integrations-0.0.2.dist-info/RECORD
