Metadata-Version: 2.1
Name: sentry-afone-integrations
Version: 0.0.2
Summary: All for one integerations.
Home-page: https://github.com/raylua2566/sentry-afone-integrations
Author: RayLau
Author-email: raylua2566@hotmail.com
License: MIT
Keywords: sentry webhook integrations afone diligent
Platform: UNKNOWN
Classifier: Programming Language :: Python :: 2.7
Classifier: Topic :: Utilities
Classifier: License :: OSI Approved :: MIT License
Requires-Dist: sentry (>=10.0.0)
Requires-Dist: requests
